ptera/__init__.py
ptera/interpret.py
ptera/opparse.py
ptera/overlay.py
ptera/probe.py
ptera/selector.py
ptera/tags.py
ptera/tools.py
ptera/transform.py
ptera/utils.py
ptera/version.py
ptera-1.4.1.dist-info/LICENSE
ptera-1.4.1.dist-info/WHEEL
ptera-1.4.1.dist-info/METADATA
ptera-1.4.1.dist-info/RECORD
