Metadata-Version: 2.1
Name: ptera
Version: 1.4.1
Summary: Call graph addressing library.
Home-page: https://github.com/mila-iqia/ptera
License: MIT
Author: Olivier Breuleux
Author-email: breuleux@gmail.com
Requires-Python: >=3.7,<4.0
Classifier: License :: OSI Approved :: MIT License
Classifier: Programming Language :: Python :: 3
Classifier: Programming Language :: Python :: 3.7
Classifier: Programming Language :: Python :: 3.8
Classifier: Programming Language :: Python :: 3.9
Classifier: Programming Language :: Python :: 3.10
Classifier: Programming Language :: Python :: 3.11
Requires-Dist: codefind (>=0.1.2,<0.2.0) ; python_version >= "3.8" and python_version < "4.0"
Requires-Dist: giving (>=0.4.1,<0.5.0)
Project-URL: Repository, https://github.com/mila-iqia/ptera
